relview/__init__.py
relview/doSetupStuff.py
relview/main.py
relview/usdview.py
relview/common/__init__.py
relview/common/customizationLoader.py
relview/data/NamedRelationship.py
relview/data/PrimRelationshipRecord.py
relview/data/PrimTypeFilter.py
relview/data/PropertyNameFilter.py
relview/data/RelationshipCollection.py
relview/data/RelationshipCollectionManager.py
relview/data/RelationshipFiltering.py
relview/data/RelationshipInfoCollector.py
relview/data/RelationshipNameFilter.py
relview/data/__init__.py
relview/data/decorators.py
relview/data/filterUpdating.py
relview/gui/ForceSimulationNodeLayout.py
relview/gui/NamedRelationshipDetailsWidget.py
relview/gui/NodeLayout.py
relview/gui/PrimNodeItem.py
relview/gui/RelationshipBrowser.py
relview/gui/RelationshipDetailViewer.py
relview/gui/RelationshipFilteringOptionsDialog.py
relview/gui/RelationshipNameListWidget.py
relview/gui/RelationshipRecordDetail.py
relview/gui/RelationshipScene.py
relview/gui/RelationshipView.py
relview/gui/RelationshipWireItem.py
relview/gui/__init__.py
relview/gui/appStyling.py
relview/gui/contextManagers.py
relview/gui/icons.py
relview/gui/mixins.py
relview/gui/nodeStyling.py
relview/gui/pixmapCache.py
relview/gui/svgRendererCache.py
relview/gui/utils.py
relview/gui/widgets.py
relview/icons/__init__.py
relview/icons/auto-fit.svg
relview/icons/clear.svg
relview/icons/filter.svg
relview/icons/filter_active.svg
relview/icons/frame-selected.svg
relview/icons/go-back.svg
relview/icons/go-forward.svg
relview/icons/info.svg
relview/icons/relview-window.svg
relview/icons/show-grid.svg
relview/icons/warning.svg
relview-0.1.0.data/data/share/usd/plugins/relview/resources/plugInfo.json
relview-0.1.0.dist-info/LICENSE.txt
relview-0.1.0.dist-info/METADATA
relview-0.1.0.dist-info/WHEEL
relview-0.1.0.dist-info/entry_points.txt
relview-0.1.0.dist-info/top_level.txt
relview-0.1.0.dist-info/RECORD
