Metadata-Version: 2.1
Name: relview
Version: 0.1.0
Summary: A viewer for USD relationships
Home-page: https://gitlab.com/wdas/relationship-viewer
Author-email: David Aguilar <davvid@gmail.com>, Ryan Kawahara <ryan.kawahara@gmail.com>
License: ============================================================
Platform: any
Classifier: Development Status :: 5 - Production/Stable
Classifier: Intended Audience :: Developers
Classifier: Intended Audience :: End Users/Desktop
Classifier: Programming Language :: Python :: 3
Classifier: Topic :: Software Development :: Libraries :: Python Modules
License-File: LICENSE.txt
Requires-Dist: Qt.py>=1.1.0
Requires-Dist: importlib-metadata; python_version < "3.8"
Provides-Extra: build
Requires-Dist: build; extra == "build"
Requires-Dist: twine; extra == "build"
Requires-Dist: wheel; extra == "build"
Provides-Extra: dev
Requires-Dist: cercis; extra == "dev"
Requires-Dist: pylint>=2.14.0; extra == "dev"
Provides-Extra: docs
Requires-Dist: furo; extra == "docs"
Requires-Dist: sphinx; extra == "docs"
Requires-Dist: rst.linker>=1.9; extra == "docs"
Provides-Extra: testing
Requires-Dist: pytest!=3.7.3,>=3.5; extra == "testing"
Requires-Dist: pytest-checkdocs>=1.2.3; extra == "testing"
Requires-Dist: pytest-cov; extra == "testing"
Requires-Dist: pytest-enabler>=1.0.1; extra == "testing"
